{
  "metadata": {
    "name": "LoppyToon",
    "author": "trungkhanhduong93",
    "version": 2,
    "source": "https://loppytoon.com",
    "regexp": "loppytoon\\.com\\/truyen\\/[^\\/]+\\/?$",
    "description": "LoppyToon - Truyện tranh & tiểu thuyết",
    "locale": "vi_VN",
    "tag": "nsfw",
    "type": "novel",
    "language": "javascript",
    "encrypt": true
  },
  "script": {
    "home": "home.js",
    "genre": "genre.js",
    "detail": "detail.js",
    "search": "search.js",
    "toc": "toc.js",
    "suggest": "suggest.js",
    "comment": "comment.js",
    "chap": "chap.js"
  }
}