{
  "metadata": {
    "name": "Shinigami LN Team",
    "author": "trungkhanhduong93",
    "version": 1,
    "source": "https://shinigamilnteam.com",
    "regexp": "shinigamilnteam\\.com\\/truyen\\/[^\\/]+\\/?$",
    "description": "Shinigami - Light Novel & Truyện tranh",
    "locale": "vi_VN",
    "type": "novel",
    "language": "javascript",
    "encrypt": true
  },
  "script": {
    "home": "home.js",
    "genre": "genre.js",
    "detail": "detail.js",
    "search": "search.js",
    "toc": "toc.js",
    "suggest": "suggest.js",
    "chap": "chap.js"
  }
}