{
  "metadata": {
    "name": "Mimimoe",
    "author": "trungkhanhduong93",
    "version": 6,
    "source": "https://mimimoe.moe",
    "regexp": "mimimoe\\.moe\\/g\\/[^\\/]+\\/?$",
    "description": "Mimimoe - Truyện tranh 18+",
    "locale": "vi_VN",
    "tag": "nsfw",
    "type": "comic",
    "language": "javascript",
    "encrypt": true
  },
  "script": {
    "home": "home.js",
    "genre": "genre.js",
    "detail": "detail.js",
    "search": "search.js",
    "toc": "toc.js",
    "chap": "chap.js"
  }
}